[
  {
    "DESTINATION": "Indian Creek",
    "DIRECTION": "E",
    "EVENT_TIME": "12/10/2017 12:58:00 AM",
    "LINE": "BLUE",
    "NEXT_ARR": "12:58:09 AM",
    "STATION": "INMAN PARK STATION",
    "TRAIN_ID": "102026",
    "WAITING_SECONDS": "-41",
    "WAITING_TIME": "Boarding"
  },
  {
    "DESTINATION": "Doraville",
    "DIRECTION": "N",
    "EVENT_TIME": "12/10/2017 12:58:40 AM",
    "LINE": "GOLD",
    "NEXT_ARR": "12:58:49 AM",
    "STATION": "CIVIC CENTER STATION",
    "TRAIN_ID": "305326",
    "WAITING_SECONDS": "-1",
    "WAITING_TIME": "Boarding"
  },
  {
    "DESTINATION": "Airport",
    "DIRECTION": "S",
    "EVENT_TIME": "12/10/2017 12:58:31 AM",
    "LINE": "GOLD",
    "NEXT_ARR": "12:58:54 AM",
    "STATION": "MIDTOWN STATION",
    "TRAIN_ID": "306506",
    "WAITING_SECONDS": "4",
    "WAITING_TIME": "Arriving"
  },
  {
    "DESTINATION": "Hamilton E Holmes",
    "DIRECTION": "W",
    "EVENT_TIME": "12/10/2017 12:58:45 AM",
    "LINE": "BLUE",
    "NEXT_ARR": "12:59:07 AM",
    "STATION": "WEST LAKE STATION",
    "TRAIN_ID": "103206",
    "WAITING_SECONDS": "17",
    "WAITING_TIME": "Arriving"
  },
  {
    "DESTINATION": "Airport",
    "DIRECTION": "S",
    "EVENT_TIME": "12/10/2017 12:58:36 AM",
    "LINE": "GOLD",
    "NEXT_ARR": "12:59:40 AM",
    "STATION": "CHAMBLEE STATION",
    "TRAIN_ID": "303506",
    "WAITING_SECONDS": "50",
    "WAITING_TIME": "Arriving"
  },
  {
    "DESTINATION": "Hamilton E Holmes",
    "DIRECTION": "W",
    "EVENT_TIME": "12/10/2017 12:58:44 AM",
    "LINE": "BLUE",
    "NEXT_ARR": "12:59:52 AM",
    "STATION": "INMAN PARK STATION",
    "TRAIN_ID": "104206",
    "WAITING_SECONDS": "62",
    "WAITING_TIME": "Arriving"
  },
  {
    "DESTINATION": "Indian Creek",
    "DIRECTION": "E",
    "EVENT_TIME": "12/10/2017 12:58:00 AM",
    "LINE": "BLUE",
    "NEXT_ARR": "01:00:04 AM",
    "STATION": "EDGEWOOD CANDLER PARK STATION",
    "TRAIN_ID": "102026",
    "WAITING_SECONDS": "74",
    "WAITING_TIME": "Arriving"
  },
  {
    "DESTINATION": "Doraville",
    "DIRECTION": "N",
    "EVENT_TIME": "12/10/2017 12:58:40 AM",
    "LINE": "GOLD",
    "NEXT_ARR": "01:00:08 AM",
    "STATION": "NORTH AVE STATION",
    "TRAIN_ID": "305326",
    "WAITING_SECONDS": "78",
    "WAITING_TIME": "Arriving"
  },
  {
    "DESTINATION": "Lindbergh",
    "DIRECTION": "S",
    "EVENT_TIME": "12/10/2017 12:58:41 AM",
    "LINE": "RED",
    "NEXT_ARR": "01:00:12 AM",
    "STATION": "LINDBERGH STATION",
    "TRAIN_ID": "403366",
    "WAITING_SECONDS": "82",
    "WAITING_TIME": "Arriving"
  },
  {
    "DESTINATION": "Airport",
    "DIRECTION": "S",
    "EVENT_TIME": "12/10/2017 12:58:31 AM",
    "LINE": "GOLD",
    "NEXT_ARR": "01:00:31 AM",
    "STATION": "NORTH AVE STATION",
    "TRAIN_ID": "306506",
    "WAITING_SECONDS": "101",
    "WAITING_TIME": "1 min"
  },
  {
    "DESTINATION": "North Springs",
    "DIRECTION": "N",
    "EVENT_TIME": "12/10/2017 12:58:42 AM",
    "LINE": "RED",
    "NEXT_ARR": "01:00:47 AM",
    "STATION": "BUCKHEAD STATION",
    "TRAIN_ID": "402306",
    "WAITING_SECONDS": "117",
    "WAITING_TIME": "1 min"
  },
  {
    "DESTINATION": "Bankhead",
    "DIRECTION": "W",
    "EVENT_TIME": "12/10/2017 12:58:44 AM",
    "LINE": "GREEN",
    "NEXT_ARR": "01:00:48 AM",
    "STATION": "BANKHEAD STATION",
    "TRAIN_ID": "201252",
    "WAITING_SECONDS": "118",
    "WAITING_TIME": "1 min"
  },
  {
    "DESTINATION": "Doraville",
    "DIRECTION": "N",
    "EVENT_TIME": "12/10/2017 12:58:40 AM",
    "LINE": "GOLD",
    "NEXT_ARR": "01:01:39 AM",
    "STATION": "MIDTOWN STATION",
    "TRAIN_ID": "305326",
    "WAITING_SECONDS": "169",
    "WAITING_TIME": "2 min"
  },
  {
    "DESTINATION": "Hamilton E Holmes",
    "DIRECTION": "W",
    "EVENT_TIME": "12/10/2017 12:58:45 AM",
    "LINE": "BLUE",
    "NEXT_ARR": "01:01:42 AM",
    "STATION": "HAMILTON E HOLMES STATION",
    "TRAIN_ID": "103206",
    "WAITING_SECONDS": "172",
    "WAITING_TIME": "2 min"
  },
  {
    "DESTINATION": "Airport",
    "DIRECTION": "S",
    "EVENT_TIME": "12/10/2017 12:58:31 AM",
    "LINE": "GOLD",
    "NEXT_ARR": "01:02:15 AM",
    "STATION": "CIVIC CENTER STATION",
    "TRAIN_ID": "306506",
    "WAITING_SECONDS": "205",
    "WAITING_TIME": "2 min"
  },
  {
    "DESTINATION": "Hamilton E Holmes",
    "DIRECTION": "W",
    "EVENT_TIME": "12/10/2017 12:58:44 AM",
    "LINE": "BLUE",
    "NEXT_ARR": "01:02:21 AM",
    "STATION": "KING MEMORIAL STATION",
    "TRAIN_ID": "104206",
    "WAITING_SECONDS": "211",
    "WAITING_TIME": "3 min"
  },
  {
    "DESTINATION": "Indian Creek",
    "DIRECTION": "E",
    "EVENT_TIME": "12/10/2017 12:58:00 AM",
    "LINE": "BLUE",
    "NEXT_ARR": "01:02:56 AM",
    "STATION": "EAST LAKE STATION",
    "TRAIN_ID": "102026",
    "WAITING_SECONDS": "246",
    "WAITING_TIME": "3 min"
  },
  {
    "DESTINATION": "Doraville",
    "DIRECTION": "N",
    "EVENT_TIME": "12/10/2017 12:58:40 AM",
    "LINE": "GOLD",
    "NEXT_ARR": "01:03:12 AM",
    "STATION": "ARTS CENTER STATION",
    "TRAIN_ID": "305326",
    "WAITING_SECONDS": "262",
    "WAITING_TIME": "3 min"
  },
  {
    "DESTINATION": "Airport",
    "DIRECTION": "S",
    "EVENT_TIME": "12/10/2017 12:58:36 AM",
    "LINE": "GOLD",
    "NEXT_ARR": "01:03:19 AM",
    "STATION": "BROOKHAVEN STATION",
    "TRAIN_ID": "303506",
    "WAITING_SECONDS": "269",
    "WAITING_TIME": "3 min"
  },
  {
    "DESTINATION": "Airport",
    "DIRECTION": "S",
    "EVENT_TIME": "12/10/2017 12:58:31 AM",
    "LINE": "GOLD",
    "NEXT_ARR": "01:03:27 AM",
    "STATION": "PEACHTREE CENTER STATION",
    "TRAIN_ID": "306506",
    "WAITING_SECONDS": "277",
    "WAITING_TIME": "4 min"
  },
  {
    "DESTINATION": "Lindbergh",
    "DIRECTION": "S",
    "EVENT_TIME": "12/10/2017 12:58:41 AM",
    "LINE": "RED",
    "NEXT_ARR": "01:04:02 AM",
    "STATION": "ARTS CENTER STATION",
    "TRAIN_ID": "403366",
    "WAITING_SECONDS": "312",
    "WAITING_TIME": "4 min"
  },
  {
    "DESTINATION": "Hamilton E Holmes",
    "DIRECTION": "W",
    "EVENT_TIME": "12/10/2017 12:58:44 AM",
    "LINE": "BLUE",
    "NEXT_ARR": "01:04:18 AM",
    "STATION": "GEORGIA STATE STATION",
    "TRAIN_ID": "104206",
    "WAITING_SECONDS": "328",
    "WAITING_TIME": "4 min"
  },
  {
    "DESTINATION": "Lindbergh",
    "DIRECTION": "S",
    "EVENT_TIME": "12/10/2017 12:58:41 AM",
    "LINE": "RED",
    "NEXT_ARR": "01:05:22 AM",
    "STATION": "MIDTOWN STATION",
    "TRAIN_ID": "403366",
    "WAITING_SECONDS": "392",
    "WAITING_TIME": "6 min"
  },
  {
    "DESTINATION": "Airport",
    "DIRECTION": "S",
    "EVENT_TIME": "12/10/2017 12:58:31 AM",
    "LINE": "GOLD",
    "NEXT_ARR": "01:05:35 AM",
    "STATION": "FIVE POINTS STATION",
    "TRAIN_ID": "306506",
    "WAITING_SECONDS": "405",
    "WAITING_TIME": "6 min"
  },
  {
    "DESTINATION": "Hamilton E Holmes",
    "DIRECTION": "W",
    "EVENT_TIME": "12/10/2017 12:58:44 AM",
    "LINE": "BLUE",
    "NEXT_ARR": "01:05:40 AM",
    "STATION": "FIVE POINTS STATION",
    "TRAIN_ID": "104206",
    "WAITING_SECONDS": "410",
    "WAITING_TIME": "6 min"
  },
  {
    "DESTINATION": "Airport",
    "DIRECTION": "S",
    "EVENT_TIME": "12/10/2017 12:58:36 AM",
    "LINE": "GOLD",
    "NEXT_ARR": "01:06:01 AM",
    "STATION": "LENOX STATION",
    "TRAIN_ID": "303506",
    "WAITING_SECONDS": "431",
    "WAITING_TIME": "6 min"
  },
  {
    "DESTINATION": "Indian Creek",
    "DIRECTION": "E",
    "EVENT_TIME": "12/10/2017 12:58:00 AM",
    "LINE": "BLUE",
    "NEXT_ARR": "01:06:20 AM",
    "STATION": "DECATUR STATION",
    "TRAIN_ID": "102026",
    "WAITING_SECONDS": "450",
    "WAITING_TIME": "7 min"
  },
  {
    "DESTINATION": "North Springs",
    "DIRECTION": "N",
    "EVENT_TIME": "12/10/2017 12:58:42 AM",
    "LINE": "RED",
    "NEXT_ARR": "01:06:22 AM",
    "STATION": "MEDICAL CENTER STATION",
    "TRAIN_ID": "402306",
    "WAITING_SECONDS": "452",
    "WAITING_TIME": "7 min"
  },
  {
    "DESTINATION": "Doraville",
    "DIRECTION": "N",
    "EVENT_TIME": "12/10/2017 12:58:40 AM",
    "LINE": "GOLD",
    "NEXT_ARR": "01:06:44 AM",
    "STATION": "LINDBERGH STATION",
    "TRAIN_ID": "305326",
    "WAITING_SECONDS": "474",
    "WAITING_TIME": "7 min"
  },
  {
    "DESTINATION": "Lindbergh",
    "DIRECTION": "S",
    "EVENT_TIME": "12/10/2017 12:58:41 AM",
    "LINE": "RED",
    "NEXT_ARR": "01:06:59 AM",
    "STATION": "NORTH AVE STATION",
    "TRAIN_ID": "403366",
    "WAITING_SECONDS": "489",
    "WAITING_TIME": "7 min"
  },
  {
    "DESTINATION": "Hamilton E Holmes",
    "DIRECTION": "W",
    "EVENT_TIME": "12/10/2017 12:58:44 AM",
    "LINE": "BLUE",
    "NEXT_ARR": "01:07:11 AM",
    "STATION": "OMNI DOME STATION",
    "TRAIN_ID": "104206",
    "WAITING_SECONDS": "501",
    "WAITING_TIME": "7 min"
  },
  {
    "DESTINATION": "Airport",
    "DIRECTION": "S",
    "EVENT_TIME": "12/10/2017 12:58:31 AM",
    "LINE": "GOLD",
    "NEXT_ARR": "01:07:21 AM",
    "STATION": "GARNETT STATION",
    "TRAIN_ID": "306506",
    "WAITING_SECONDS": "511",
    "WAITING_TIME": "8 min"
  },
  {
    "DESTINATION": "Hamilton E Holmes",
    "DIRECTION": "W",
    "EVENT_TIME": "12/10/2017 12:58:44 AM",
    "LINE": "BLUE",
    "NEXT_ARR": "01:08:22 AM",
    "STATION": "VINE CITY STATION",
    "TRAIN_ID": "104206",
    "WAITING_SECONDS": "572",
    "WAITING_TIME": "9 min"
  },
  {
    "DESTINATION": "North Springs",
    "DIRECTION": "N",
    "EVENT_TIME": "12/10/2017 12:58:42 AM",
    "LINE": "RED",
    "NEXT_ARR": "01:08:29 AM",
    "STATION": "DUNWOODY STATION",
    "TRAIN_ID": "402306",
    "WAITING_SECONDS": "579",
    "WAITING_TIME": "9 min"
  },
  {
    "DESTINATION": "Indian Creek",
    "DIRECTION": "E",
    "EVENT_TIME": "12/10/2017 12:58:00 AM",
    "LINE": "BLUE",
    "NEXT_ARR": "01:08:39 AM",
    "STATION": "AVONDALE STATION",
    "TRAIN_ID": "102026",
    "WAITING_SECONDS": "589",
    "WAITING_TIME": "9 min"
  },
  {
    "DESTINATION": "Lindbergh",
    "DIRECTION": "S",
    "EVENT_TIME": "12/10/2017 12:58:41 AM",
    "LINE": "RED",
    "NEXT_ARR": "01:08:43 AM",
    "STATION": "CIVIC CENTER STATION",
    "TRAIN_ID": "403366",
    "WAITING_SECONDS": "593",
    "WAITING_TIME": "9 min"
  },
  {
    "DESTINATION": "Airport",
    "DIRECTION": "S",
    "EVENT_TIME": "12/10/2017 12:58:36 AM",
    "LINE": "GOLD",
    "NEXT_ARR": "01:09:18 AM",
    "STATION": "LINDBERGH STATION",
    "TRAIN_ID": "303506",
    "WAITING_SECONDS": "628",
    "WAITING_TIME": "9 min"
  },
  {
    "DESTINATION": "Hamilton E Holmes",
    "DIRECTION": "W",
    "EVENT_TIME": "12/10/2017 12:58:44 AM",
    "LINE": "BLUE",
    "NEXT_ARR": "01:09:52 AM",
    "STATION": "ASHBY STATION",
    "TRAIN_ID": "104206",
    "WAITING_SECONDS": "662",
    "WAITING_TIME": "10 min"
  },
  {
    "DESTINATION": "Lindbergh",
    "DIRECTION": "S",
    "EVENT_TIME": "12/10/2017 12:58:41 AM",
    "LINE": "RED",
    "NEXT_ARR": "01:09:55 AM",
    "STATION": "PEACHTREE CENTER STATION",
    "TRAIN_ID": "403366",
    "WAITING_SECONDS": "665",
    "WAITING_TIME": "10 min"
  },
  {
    "DESTINATION": "Airport",
    "DIRECTION": "S",
    "EVENT_TIME": "12/10/2017 12:58:31 AM",
    "LINE": "GOLD",
    "NEXT_ARR": "01:09:55 AM",
    "STATION": "WEST END STATION",
    "TRAIN_ID": "306506",
    "WAITING_SECONDS": "665",
    "WAITING_TIME": "10 min"
  },
  {
    "DESTINATION": "North Springs",
    "DIRECTION": "N",
    "EVENT_TIME": "12/10/2017 12:58:42 AM",
    "LINE": "RED",
    "NEXT_ARR": "01:10:23 AM",
    "STATION": "SANDY SPRINGS STATION",
    "TRAIN_ID": "402306",
    "WAITING_SECONDS": "693",
    "WAITING_TIME": "11 min"
  },
  {
    "DESTINATION": "Doraville",
    "DIRECTION": "N",
    "EVENT_TIME": "12/10/2017 12:58:40 AM",
    "LINE": "GOLD",
    "NEXT_ARR": "01:10:33 AM",
    "STATION": "LENOX STATION",
    "TRAIN_ID": "305326",
    "WAITING_SECONDS": "703",
    "WAITING_TIME": "11 min"
  },
  {
    "DESTINATION": "Indian Creek",
    "DIRECTION": "E",
    "EVENT_TIME": "12/10/2017 12:58:00 AM",
    "LINE": "BLUE",
    "NEXT_ARR": "01:11:37 AM",
    "STATION": "KENSINGTON STATION",
    "TRAIN_ID": "102026",
    "WAITING_SECONDS": "767",
    "WAITING_TIME": "12 min"
  },
  {
    "DESTINATION": "Hamilton E Holmes",
    "DIRECTION": "W",
    "EVENT_TIME": "12/10/2017 12:58:44 AM",
    "LINE": "BLUE",
    "NEXT_ARR": "01:12:00 AM",
    "STATION": "WEST LAKE STATION",
    "TRAIN_ID": "104206",
    "WAITING_SECONDS": "790",
    "WAITING_TIME": "12 min"
  },
  {
    "DESTINATION": "Lindbergh",
    "DIRECTION": "S",
    "EVENT_TIME": "12/10/2017 12:58:41 AM",
    "LINE": "RED",
    "NEXT_ARR": "01:12:03 AM",
    "STATION": "FIVE POINTS STATION",
    "TRAIN_ID": "403366",
    "WAITING_SECONDS": "793",
    "WAITING_TIME": "12 min"
  },
  {
    "DESTINATION": "Airport",
    "DIRECTION": "S",
    "EVENT_TIME": "12/10/2017 12:58:31 AM",
    "LINE": "GOLD",
    "NEXT_ARR": "01:12:28 AM",
    "STATION": "OAKLAND CITY STATION",
    "TRAIN_ID": "306506",
    "WAITING_SECONDS": "818",
    "WAITING_TIME": "13 min"
  },
  {
    "DESTINATION": "North Springs",
    "DIRECTION": "N",
    "EVENT_TIME": "12/10/2017 12:58:42 AM",
    "LINE": "RED",
    "NEXT_ARR": "01:13:00 AM",
    "STATION": "NORTH SPRINGS STATION",
    "TRAIN_ID": "402306",
    "WAITING_SECONDS": "850",
    "WAITING_TIME": "13 min"
  },
  {
    "DESTINATION": "Doraville",
    "DIRECTION": "N",
    "EVENT_TIME": "12/10/2017 12:58:40 AM",
    "LINE": "GOLD",
    "NEXT_ARR": "01:13:08 AM",
    "STATION": "BROOKHAVEN STATION",
    "TRAIN_ID": "305326",
    "WAITING_SECONDS": "858",
    "WAITING_TIME": "13 min"
  },
  {
    "DESTINATION": "Airport",
    "DIRECTION": "S",
    "EVENT_TIME": "12/10/2017 12:58:36 AM",
    "LINE": "GOLD",
    "NEXT_ARR": "01:13:08 AM",
    "STATION": "ARTS CENTER STATION",
    "TRAIN_ID": "303506",
    "WAITING_SECONDS": "858",
    "WAITING_TIME": "13 min"
  },
  {
    "DESTINATION": "Lindbergh",
    "DIRECTION": "S",
    "EVENT_TIME": "12/10/2017 12:58:41 AM",
    "LINE": "RED",
    "NEXT_ARR": "01:13:49 AM",
    "STATION": "GARNETT STATION",
    "TRAIN_ID": "403366",
    "WAITING_SECONDS": "899",
    "WAITING_TIME": "14 min"
  },
  {
    "DESTINATION": "Indian Creek",
    "DIRECTION": "E",
    "EVENT_TIME": "12/10/2017 12:58:00 AM",
    "LINE": "BLUE",
    "NEXT_ARR": "01:14:13 AM",
    "STATION": "INDIAN CREEK STATION",
    "TRAIN_ID": "102026",
    "WAITING_SECONDS": "923",
    "WAITING_TIME": "14 min"
  },
  {
    "DESTINATION": "Airport",
    "DIRECTION": "S",
    "EVENT_TIME": "12/10/2017 12:58:36 AM",
    "LINE": "GOLD",
    "NEXT_ARR": "01:14:28 AM",
    "STATION": "MIDTOWN STATION",
    "TRAIN_ID": "303506",
    "WAITING_SECONDS": "938",
    "WAITING_TIME": "15 min"
  },
  {
    "DESTINATION": "Hamilton E Holmes",
    "DIRECTION": "W",
    "EVENT_TIME": "12/10/2017 12:58:44 AM",
    "LINE": "BLUE",
    "NEXT_ARR": "01:14:35 AM",
    "STATION": "HAMILTON E HOLMES STATION",
    "TRAIN_ID": "104206",
    "WAITING_SECONDS": "945",
    "WAITING_TIME": "15 min"
  },
  {
    "DESTINATION": "Airport",
    "DIRECTION": "S",
    "EVENT_TIME": "12/10/2017 12:58:31 AM",
    "LINE": "GOLD",
    "NEXT_ARR": "01:14:46 AM",
    "STATION": "LAKEWOOD STATION",
    "TRAIN_ID": "306506",
    "WAITING_SECONDS": "956",
    "WAITING_TIME": "15 min"
  },
  {
    "DESTINATION": "Airport",
    "DIRECTION": "S",
    "EVENT_TIME": "12/10/2017 12:58:36 AM",
    "LINE": "GOLD",
    "NEXT_ARR": "01:16:05 AM",
    "STATION": "NORTH AVE STATION",
    "TRAIN_ID": "303506",
    "WAITING_SECONDS": "1035",
    "WAITING_TIME": "16 min"
  },
  {
    "DESTINATION": "Lindbergh",
    "DIRECTION": "S",
    "EVENT_TIME": "12/10/2017 12:58:41 AM",
    "LINE": "RED",
    "NEXT_ARR": "01:16:23 AM",
    "STATION": "WEST END STATION",
    "TRAIN_ID": "403366",
    "WAITING_SECONDS": "1053",
    "WAITING_TIME": "17 min"
  },
  {
    "DESTINATION": "Doraville",
    "DIRECTION": "N",
    "EVENT_TIME": "12/10/2017 12:58:40 AM",
    "LINE": "GOLD",
    "NEXT_ARR": "01:16:44 AM",
    "STATION": "CHAMBLEE STATION",
    "TRAIN_ID": "305326",
    "WAITING_SECONDS": "1074",
    "WAITING_TIME": "17 min"
  },
  {
    "DESTINATION": "Airport",
    "DIRECTION": "S",
    "EVENT_TIME": "12/10/2017 12:58:31 AM",
    "LINE": "GOLD",
    "NEXT_ARR": "01:17:34 AM",
    "STATION": "EAST POINT STATION",
    "TRAIN_ID": "306506",
    "WAITING_SECONDS": "1124",
    "WAITING_TIME": "18 min"
  },
  {
    "DESTINATION": "Airport",
    "DIRECTION": "S",
    "EVENT_TIME": "12/10/2017 12:58:36 AM",
    "LINE": "GOLD",
    "NEXT_ARR": "01:17:49 AM",
    "STATION": "CIVIC CENTER STATION",
    "TRAIN_ID": "303506",
    "WAITING_SECONDS": "1139",
    "WAITING_TIME": "18 min"
  },
  {
    "DESTINATION": "Lindbergh",
    "DIRECTION": "S",
    "EVENT_TIME": "12/10/2017 12:58:41 AM",
    "LINE": "RED",
    "NEXT_ARR": "01:18:56 AM",
    "STATION": "OAKLAND CITY STATION",
    "TRAIN_ID": "403366",
    "WAITING_SECONDS": "1206",
    "WAITING_TIME": "19 min"
  },
  {
    "DESTINATION": "Airport",
    "DIRECTION": "S",
    "EVENT_TIME": "12/10/2017 12:58:36 AM",
    "LINE": "GOLD",
    "NEXT_ARR": "01:19:01 AM",
    "STATION": "PEACHTREE CENTER STATION",
    "TRAIN_ID": "303506",
    "WAITING_SECONDS": "1211",
    "WAITING_TIME": "19 min"
  },
  {
    "DESTINATION": "Doraville",
    "DIRECTION": "N",
    "EVENT_TIME": "12/10/2017 12:58:40 AM",
    "LINE": "GOLD",
    "NEXT_ARR": "01:19:45 AM",
    "STATION": "DORAVILLE STATION",
    "TRAIN_ID": "305326",
    "WAITING_SECONDS": "1255",
    "WAITING_TIME": "20 min"
  },
  {
    "DESTINATION": "Airport",
    "DIRECTION": "S",
    "EVENT_TIME": "12/10/2017 12:58:31 AM",
    "LINE": "GOLD",
    "NEXT_ARR": "01:20:17 AM",
    "STATION": "COLLEGE PARK STATION",
    "TRAIN_ID": "306506",
    "WAITING_SECONDS": "1287",
    "WAITING_TIME": "20 min"
  },
  {
    "DESTINATION": "Lindbergh",
    "DIRECTION": "S",
    "EVENT_TIME": "12/10/2017 12:58:41 AM",
    "LINE": "RED",
    "NEXT_ARR": "01:21:09 AM",
    "STATION": "LAKEWOOD STATION",
    "TRAIN_ID": "403366",
    "WAITING_SECONDS": "1339",
    "WAITING_TIME": "21 min"
  },
  {
    "DESTINATION": "Airport",
    "DIRECTION": "S",
    "EVENT_TIME": "12/10/2017 12:58:36 AM",
    "LINE": "GOLD",
    "NEXT_ARR": "01:21:09 AM",
    "STATION": "FIVE POINTS STATION",
    "TRAIN_ID": "303506",
    "WAITING_SECONDS": "1339",
    "WAITING_TIME": "21 min"
  },
  {
    "DESTINATION": "Airport",
    "DIRECTION": "S",
    "EVENT_TIME": "12/10/2017 12:58:31 AM",
    "LINE": "GOLD",
    "NEXT_ARR": "01:22:38 AM",
    "STATION": "AIRPORT STATION",
    "TRAIN_ID": "306506",
    "WAITING_SECONDS": "1428",
    "WAITING_TIME": "23 min"
  },
  {
    "DESTINATION": "Airport",
    "DIRECTION": "S",
    "EVENT_TIME": "12/10/2017 12:58:36 AM",
    "LINE": "GOLD",
    "NEXT_ARR": "01:22:55 AM",
    "STATION": "GARNETT STATION",
    "TRAIN_ID": "303506",
    "WAITING_SECONDS": "1445",
    "WAITING_TIME": "23 min"
  },
  {
    "DESTINATION": "Lindbergh",
    "DIRECTION": "S",
    "EVENT_TIME": "12/10/2017 12:58:41 AM",
    "LINE": "RED",
    "NEXT_ARR": "01:23:57 AM",
    "STATION": "EAST POINT STATION",
    "TRAIN_ID": "403366",
    "WAITING_SECONDS": "1507",
    "WAITING_TIME": "24 min"
  },
  {
    "DESTINATION": "Airport",
    "DIRECTION": "S",
    "EVENT_TIME": "12/10/2017 12:58:36 AM",
    "LINE": "GOLD",
    "NEXT_ARR": "01:25:29 AM",
    "STATION": "WEST END STATION",
    "TRAIN_ID": "303506",
    "WAITING_SECONDS": "1599",
    "WAITING_TIME": "26 min"
  },
  {
    "DESTINATION": "Lindbergh",
    "DIRECTION": "S",
    "EVENT_TIME": "12/10/2017 12:58:41 AM",
    "LINE": "RED",
    "NEXT_ARR": "01:26:40 AM",
    "STATION": "COLLEGE PARK STATION",
    "TRAIN_ID": "403366",
    "WAITING_SECONDS": "1670",
    "WAITING_TIME": "27 min"
  },
  {
    "DESTINATION": "Airport",
    "DIRECTION": "S",
    "EVENT_TIME": "12/10/2017 12:58:36 AM",
    "LINE": "GOLD",
    "NEXT_ARR": "01:28:02 AM",
    "STATION": "OAKLAND CITY STATION",
    "TRAIN_ID": "303506",
    "WAITING_SECONDS": "1752",
    "WAITING_TIME": "28 min"
  },
  {
    "DESTINATION": "Lindbergh",
    "DIRECTION": "S",
    "EVENT_TIME": "12/10/2017 12:58:41 AM",
    "LINE": "RED",
    "NEXT_ARR": "01:28:58 AM",
    "STATION": "AIRPORT STATION",
    "TRAIN_ID": "403366",
    "WAITING_SECONDS": "1808",
    "WAITING_TIME": "29 min"
  }
]